LICENSE
MANIFEST.in
README.md
dendrotox.py
dendrotox_alert.py
dendrotox_alert_call.py
dendrotox_call_microphone.py
dendrotox_example_bot.py
dendrotox_example_bot_print_last_message.py
setup.py
dendrotox.egg-info/PKG-INFO
dendrotox.egg-info/SOURCES.txt
dendrotox.egg-info/dependency_links.txt
dendrotox.egg-info/entry_points.txt
dendrotox.egg-info/requires.txt
dendrotox.egg-info/top_level.txt