Metadata-Version: 1.0
Name: dendrotox
Version: 2018.3.3.125
Summary: Python interface to Tox distributed communications
Home-page: https://github.com/wdbm/dendrotox
Author: Will Breaden Madden
Author-email: wbm@protonmail.ch
License: GPLv3
Platform: UNKNOWN
